{"50XT5KNy3Hox0dV5U/jZww==":"mbr-1920x1280.jpg","MWV8jinaZ21JwwZgzAEr/A==":"mbr-1368x909.jpg","4+0195GhLe4S3KX83h7qhw==":"mbr-1920x1271.jpg","kIdif0QIwNns1p9z5Wwedw==":"logo_transparent-144x144.png","EzL9ecfo93orraagWU7nsQ==":"logo_transparent-1-144x144.png","9UBEigvezg7EY2g2tEHd0Q==":"logo_transparent-192x192.png","1r3u1L34AwnzlmU86yQc6Q==":"logo_transparent-1-192x192.png","CL7PAnyIFyxsTq5Hw6B/Vg==":"logo_transparent-142x142.png","GcgQqDUBOrBC0zQ3hj/o5g==":"logo_transparent-1-142x142.png","USyPfAew+daF5V/TTB6UAw==":"mbr-1368x912.jpg","PzgZQPpVPP3E7mo2jirr1w==":"1628627-1607x856.jpg","ADXqS2W6r2kW/vKR1VQcSA==":"mbr-712x475.jpg","kGa9lNtvjBuKMUsrwds+Tg==":"mbr-1-712x475.jpg","64vAGc5wSgH7/5CR7Ko7TQ==":"mbr-712x427.jpg","IFex5uycsANn7QgrfIePmA==":"mbr-2-712x475.jpg","7warlKNC+ZITLzHS3yT5mw==":"mbr-712x317.jpg","vNSpAIsGIvzdfZwnGdhxPQ==":"mbr-712x307.jpg","PgEBx4E3q7nZl/NQpt/RxQ==":"mbr-712x355.jpg","EvztyLzh/P/IR1Qh5P5NmA==":"mbr-712x453.jpg","9vAMLhL/PaCFAjNgwIbajg==":"mbr-3-712x475.jpg","HGRDR0tkJlgitEFstkSE/w==":"logo_transparent-2-142x142.png","SBJ9Ht4ZmJOknsgK7zj7tA==":"logo_transparent-2-144x144.png","s+89XFxrEv7ZTEOHJkuEUA==":"mbr-1-1920x1280.jpg","bBOb7/VzSdN/FkJM4F6xbQ==":"mbr-1920x1188.jpg"}